qase/__init__.py
qase/api_client_v2/__init__.py
qase/api_client_v2/api_client.py
qase/api_client_v2/api_response.py
qase/api_client_v2/configuration.py
qase/api_client_v2/exceptions.py
qase/api_client_v2/py.typed
qase/api_client_v2/rest.py
qase/api_client_v2/api/__init__.py
qase/api_client_v2/api/custom_fields_api.py
qase/api_client_v2/api/results_api.py
qase/api_client_v2/models/__init__.py
qase/api_client_v2/models/base_response.py
qase/api_client_v2/models/create_results_request_v2.py
qase/api_client_v2/models/custom_field.py
qase/api_client_v2/models/custom_field_list_response.py
qase/api_client_v2/models/custom_field_list_response_all_of_result.py
qase/api_client_v2/models/custom_field_option.py
qase/api_client_v2/models/custom_field_response.py
qase/api_client_v2/models/relation_suite.py
qase/api_client_v2/models/relation_suite_item.py
qase/api_client_v2/models/result_create.py
qase/api_client_v2/models/result_create_bulk_response.py
qase/api_client_v2/models/result_create_fields.py
qase/api_client_v2/models/result_create_response.py
qase/api_client_v2/models/result_create_response_all_of_result.py
qase/api_client_v2/models/result_execution.py
qase/api_client_v2/models/result_relations.py
qase/api_client_v2/models/result_step.py
qase/api_client_v2/models/result_step_data.py
qase/api_client_v2/models/result_step_execution.py
qase/api_client_v2/models/result_step_status.py
qase/api_client_v2/models/result_steps_type.py
qase_api_v2_client-2.0.3.dist-info/METADATA
qase_api_v2_client-2.0.3.dist-info/WHEEL
qase_api_v2_client-2.0.3.dist-info/top_level.txt
qase_api_v2_client-2.0.3.dist-info/RECORD
